[
  {
    "timestamp": "2026-03-19T16:46:26.197724+00:00",
    "paper": true,
    "source": "weather",
    "market_id": "0x31e26ed699281570938216d0c3454ec80ccebc0b84af8dcd25e9cc068ffb11e5",
    "question": "Will the highest temperature in Singapore be 31\u00b0C on March 22?",
    "event_title": "Will the highest temperature in Singapore be 31\u00b0C on March 22?",
    "outcome": "YES",
    "edge": 0.454,
    "market_prob": 0.075,
    "my_estimate": 0.529,
    "bet_size": 20.0,
    "prob_before": 0.075,
    "prob_after": null,
    "url": "https://polymarket.com/event/highest-temperature-in-singapore-on-march-22-2026",
    "resolved": false,
    "result": null,
    "profit": null,
    "city": "singapore",
    "threshold_c": 31.0,
    "direction": "above",
    "date": "2026-03-31",
    "days_out": 11,
    "forecast_max_c": 31.4,
    "model_prob_raw": 0.529
  },
  {
    "timestamp": "2026-03-19T16:46:26.197991+00:00",
    "paper": true,
    "source": "weather",
    "market_id": "0x6771ec9a070d9dfa5ac82504903189a53ef6922ce8a0427edabd54db998b551f",
    "question": "Will the highest temperature in Singapore be 30\u00b0C on March 20?",
    "event_title": "Will the highest temperature in Singapore be 30\u00b0C on March 20?",
    "outcome": "YES",
    "edge": 0.4517,
    "market_prob": 0.0085,
    "my_estimate": 0.4602,
    "bet_size": 20.0,
    "prob_before": 0.0085,
    "prob_after": null,
    "url": "https://polymarket.com/event/highest-temperature-in-singapore-on-march-20-2026",
    "resolved": false,
    "result": null,
    "profit": null,
    "city": "singapore",
    "threshold_c": 30.0,
    "direction": "above",
    "date": "2026-03-30",
    "days_out": 10,
    "forecast_max_c": 29.6,
    "model_prob_raw": 0.4602
  },
  {
    "timestamp": "2026-03-19T16:46:26.198526+00:00",
    "paper": true,
    "source": "weather",
    "market_id": "0x26be6def448a7b0fd8f0c003818a10960a3fbd5aa82b1adf8826d617995815bc",
    "question": "Will the highest temperature in Madrid be 20\u00b0C on March 23?",
    "event_title": "Will the highest temperature in Madrid be 20\u00b0C on March 23?",
    "outcome": "NO",
    "edge": 0.195,
    "market_prob": 0.785,
    "my_estimate": 0.98,
    "bet_size": 20.0,
    "prob_before": 0.785,
    "prob_after": null,
    "url": "https://polymarket.com/event/highest-temperature-in-madrid-on-march-23-2026",
    "resolved": false,
    "result": null,
    "profit": null,
    "city": "madrid",
    "threshold_c": 20.0,
    "direction": "above",
    "date": "2026-03-20",
    "days_out": 0,
    "forecast_max_c": 13.6,
    "model_prob_raw": 0.02
  },
  {
    "timestamp": "2026-03-19T16:46:26.198914+00:00",
    "paper": true,
    "source": "weather",
    "market_id": "0x9489a9a8a3a6679d778ee6a8ca8dc83335eec8c671f46e04ea4740ec951a3888",
    "question": "Will the highest temperature in Madrid be 21\u00b0C on March 23?",
    "event_title": "Will the highest temperature in Madrid be 21\u00b0C on March 23?",
    "outcome": "NO",
    "edge": 0.14,
    "market_prob": 0.84,
    "my_estimate": 0.98,
    "bet_size": 20.0,
    "prob_before": 0.84,
    "prob_after": null,
    "url": "https://polymarket.com/event/highest-temperature-in-madrid-on-march-23-2026",
    "resolved": false,
    "result": null,
    "profit": null,
    "city": "madrid",
    "threshold_c": 21.0,
    "direction": "above",
    "date": "2026-03-21",
    "days_out": 1,
    "forecast_max_c": 14.0,
    "model_prob_raw": 0.02
  },
  {
    "timestamp": "2026-03-19T16:46:26.199513+00:00",
    "paper": true,
    "source": "weather",
    "market_id": "0xe02ba1dec4cf0c20f4a8c4b0d9c2137df55336a4158a92f2fea26d0dac5c7b3e",
    "question": "Will the highest temperature in Madrid be 22\u00b0C on March 23?",
    "event_title": "Will the highest temperature in Madrid be 22\u00b0C on March 23?",
    "outcome": "NO",
    "edge": 0.12,
    "market_prob": 0.86,
    "my_estimate": 0.98,
    "bet_size": 20.0,
    "prob_before": 0.86,
    "prob_after": null,
    "url": "https://polymarket.com/event/highest-temperature-in-madrid-on-march-23-2026",
    "resolved": false,
    "result": null,
    "profit": null,
    "city": "madrid",
    "threshold_c": 22.0,
    "direction": "above",
    "date": "2026-03-22",
    "days_out": 2,
    "forecast_max_c": 18.4,
    "model_prob_raw": 0.02
  }
]